pandahandler/__init__.py
pandahandler/indexes.py
pandahandler/schema.py
pandahandler/tabulation.py
pandahandler/frames/__init__.py
pandahandler/frames/columns.py
pandahandler/frames/constants.py
pandahandler/frames/joiners.py
pandahandler/frames/decorators/__init__.py
pandahandler/frames/decorators/demo.py
pandahandler/frames/decorators/framesize.py
pandahandler/frames/filtering/__init__.py
pandahandler/frames/filtering/filters.py
pandahandler/frames/filtering/masks.py
pandahandler/frames/filtering/masktools.py
pandahandler/frames/filtering/demo/processing.py
pandahandler/frames/filtering/demo/run.py
pandahandler/sklearn/__init__.py
pandahandler/sklearn/transforms/categoricals.py
pandahandler-0.8.1.dist-info/METADATA
pandahandler-0.8.1.dist-info/WHEEL
pandahandler-0.8.1.dist-info/licenses/LICENSE
pandahandler-0.8.1.dist-info/RECORD
