Metadata-Version: 2.4
Name: pandahandler
Version: 0.8.1
Summary: Tools for handling pandas objects.
Project-URL: Source, https://github.com/zkurtz/pandahandler
Author-email: Zach Kurtz <zkurtz@gmail.com>
License-File: LICENSE
Requires-Python: >=3.10
Requires-Dist: attrs>=24.3.0
Requires-Dist: pandas>=1.5.0
Requires-Dist: sigfig>=1.3.18
Requires-Dist: typing-extensions>=4.5.0
